<?xml version="1.0"?>

<model-hints>
	<model name="com.xtivia.training.servicebuilder.model.Book">
		<field name="uuid" type="String" />
		<field name="id" type="long" />
		<field name="name" type="String" />
		<field name="isbn" type="long" />
		<field name="author" type="String" />
		<field name="summary" type="String" />
		<field name="status" type="int" />
		<field name="statusByUserId" type="long" />
		<field name="statusByUserName" type="String" />
		<field name="statusDate" type="Date" />
		<field name="companyId" type="long" />
		<field name="groupId" type="long" />
		<field name="userId" type="long" />
	</model>
</model-hints>